odoo9_addon_purchase_stock_picking_return_invoicing_open_qty-9.0.1.0.0-py2.7-nspkg.pth
odoo9_addon_purchase_stock_picking_return_invoicing_open_qty-9.0.1.0.0.dist-info/DESCRIPTION.rst
odoo9_addon_purchase_stock_picking_return_invoicing_open_qty-9.0.1.0.0.dist-info/METADATA
odoo9_addon_purchase_stock_picking_return_invoicing_open_qty-9.0.1.0.0.dist-info/RECORD
odoo9_addon_purchase_stock_picking_return_invoicing_open_qty-9.0.1.0.0.dist-info/WHEEL
odoo9_addon_purchase_stock_picking_return_invoicing_open_qty-9.0.1.0.0.dist-info/metadata.json
odoo9_addon_purchase_stock_picking_return_invoicing_open_qty-9.0.1.0.0.dist-info/namespace_packages.txt
odoo9_addon_purchase_stock_picking_return_invoicing_open_qty-9.0.1.0.0.dist-info/top_level.txt
odoo_addons/purchase_stock_picking_return_invoicing_open_qty/README.rst
odoo_addons/purchase_stock_picking_return_invoicing_open_qty/__init__.py
odoo_addons/purchase_stock_picking_return_invoicing_open_qty/__openerp__.py
odoo_addons/purchase_stock_picking_return_invoicing_open_qty/models/__init__.py
odoo_addons/purchase_stock_picking_return_invoicing_open_qty/models/purchase_order.py
odoo_addons/purchase_stock_picking_return_invoicing_open_qty/static/description/icon.png
odoo_addons/purchase_stock_picking_return_invoicing_open_qty/views/purchase_view.xml
